cosapp_lab/__init__.py
cosapp_lab/_frontend.py
cosapp_lab/_version.py
cosapp_lab/main.py
cosapp_lab/app_static/index.html
cosapp_lab/app_static/main.html
cosapp_lab/app_static/static/cosapp.gif
cosapp_lab/app_static/static/cosapp.svg
cosapp_lab/app_static/static/green.svg
cosapp_lab/app_static/static/red.svg
cosapp_lab/app_static/static/splash.css
cosapp_lab/app_static/static/style.css
cosapp_lab/app_static/static/url.js
cosapp_lab/app_static/static/dist/index.js
cosapp_lab/app_static/static/dist/index.js.LICENSE.txt
cosapp_lab/app_static/static/dist/library.js
cosapp_lab/app_static/static/dist/library.js.LICENSE.txt
cosapp_lab/module/__init__.py
cosapp_lab/module/handlers.py
cosapp_lab/module/module_server.py
cosapp_lab/module/templates/404.html
cosapp_lab/script/__init__.py
cosapp_lab/script/cosapp_init.py
cosapp_lab/script/cosapp_jupyterlab.py
cosapp_lab/script/cosapp_module.py
cosapp_lab/script/tests/test_cosapp_module.py
cosapp_lab/script/tests/Mock_Module/DefaultCosappModule.py
cosapp_lab/script/tests/Mock_Module/NonCosappModule.py
cosapp_lab/script/tests/Mock_Module/WorkingCosappModule.py
cosapp_lab/server/__init__.py
cosapp_lab/server/cosapp_kernel.py
cosapp_lab/server/cosapp_server.py
cosapp_lab/utils/__init__.py
cosapp_lab/utils/copy_extension.py
cosapp_lab/utils/helpers.py
cosapp_lab/utils/templates/file_template/port.j2
cosapp_lab/utils/templates/file_template/system.j2
cosapp_lab/widgets/__init__.py
cosapp_lab/widgets/base/__init__.py
cosapp_lab/widgets/base/base_component.py
cosapp_lab/widgets/base/base_widget.py
cosapp_lab/widgets/chartwidget/__init__.py
cosapp_lab/widgets/chartwidget/chart_component.py
cosapp_lab/widgets/chartwidget/chart_widget.py
cosapp_lab/widgets/connectionwidget/__init__.py
cosapp_lab/widgets/connectionwidget/connection_widget.py
cosapp_lab/widgets/controllerwidget/__init__.py
cosapp_lab/widgets/controllerwidget/controller_component.py
cosapp_lab/widgets/controllerwidget/controller_widget.py
cosapp_lab-1.0.0.dist-info/METADATA
cosapp_lab-1.0.0.dist-info/WHEEL
cosapp_lab-1.0.0.dist-info/entry_points.txt
cosapp_lab-1.0.0.dist-info/licenses/AUTHORS.rst
cosapp_lab-1.0.0.dist-info/licenses/LICENSE
cosapp_lab-1.0.0.dist-info/RECORD
