Metadata-Version: 2.4
Name: cosapp_lab
Version: 1.0.0
Dynamic: Keywords
Summary: Toolbox for managing and deploying CoSApp powered dashboards.
Project-URL: Homepage, https://gitlab.com/cosapp/cosapp_lab
Project-URL: Bug Tracker, https://gitlab.com/cosapp/cosapp_lab/issues
Project-URL: Repository, https://gitlab.com/cosapp/cosapp_lab.git
Author-email: CoSApp Team <etienne.lac@safrangroup.com>
License: Copyright (C) 2017-2021 Safran SA - All Rights Reserved
License-File: AUTHORS.rst
License-File: LICENSE
Classifier: Framework :: Jupyter
Classifier: Framework :: Jupyter :: JupyterLab
Classifier: Framework :: Jupyter :: JupyterLab :: 4
Classifier: Framework :: Jupyter :: JupyterLab :: Extensions
Classifier: Framework :: Jupyter :: JupyterLab :: Extensions :: Prebuilt
Classifier: License :: OSI Approved :: BSD License
Classifier: Programming Language :: Python
Classifier: Programming Language :: Python :: 3
Classifier: Programming Language :: Python :: 3.8
Classifier: Programming Language :: Python :: 3.9
Classifier: Programming Language :: Python :: 3.10
Classifier: Programming Language :: Python :: 3.11
Classifier: Programming Language :: Python :: 3.12
Requires-Python: >=3.8
Requires-Dist: click
Requires-Dist: cookiecutter
Requires-Dist: cosapp>=1
Requires-Dist: ipywidgets>=8
Requires-Dist: jinja2
Requires-Dist: jupyter-client>=8
Requires-Dist: jupyter-server>=2
Requires-Dist: markdown
Requires-Dist: requests
Requires-Dist: tornado>=6.1.0
Provides-Extra: test
Requires-Dist: ipykernel; extra == 'test'
Requires-Dist: nbconvert; extra == 'test'
Requires-Dist: pytest; extra == 'test'
